CONTRIBUTING.md
CONTRIBUTORS
Dockerfile
LICENSE.txt
MANIFEST.in
NOTICE
README.rst
setup.cfg
setup.py
curator/__init__.py
curator/_version.py
curator/actions.py
curator/cli.py
curator/config_utils.py
curator/curator_cli.py
curator/exceptions.py
curator/indexlist.py
curator/logtools.py
curator/repomgrcli.py
curator/singletons.py
curator/snapshotlist.py
curator/utils.py
curator/cli_singletons/__init__.py
curator/cli_singletons/alias.py
curator/cli_singletons/allocation.py
curator/cli_singletons/close.py
curator/cli_singletons/delete.py
curator/cli_singletons/forcemerge.py
curator/cli_singletons/freeze.py
curator/cli_singletons/object_class.py
curator/cli_singletons/open_indices.py
curator/cli_singletons/replicas.py
curator/cli_singletons/restore.py
curator/cli_singletons/rollover.py
curator/cli_singletons/show.py
curator/cli_singletons/shrink.py
curator/cli_singletons/snapshot.py
curator/cli_singletons/unfreeze.py
curator/cli_singletons/utils.py
curator/defaults/__init__.py
curator/defaults/client_defaults.py
curator/defaults/filter_elements.py
curator/defaults/filtertypes.py
curator/defaults/option_defaults.py
curator/defaults/settings.py
curator/validators/__init__.py
curator/validators/actions.py
curator/validators/config_file.py
curator/validators/filters.py
curator/validators/options.py
curator/validators/schemacheck.py
docs/Changelog.rst
docs/Makefile
docs/actionclasses.rst
docs/conf.py
docs/examples.rst
docs/filters.rst
docs/index.rst
docs/objectclasses.rst
docs/utilities.rst
docs/asciidoc/about.asciidoc
docs/asciidoc/actions.asciidoc
docs/asciidoc/command-line.asciidoc
docs/asciidoc/configuration.asciidoc
docs/asciidoc/examples.asciidoc
docs/asciidoc/faq.asciidoc
docs/asciidoc/filter_elements.asciidoc
docs/asciidoc/filters.asciidoc
docs/asciidoc/ilm.asciidoc
docs/asciidoc/inc_datemath.asciidoc
docs/asciidoc/inc_filepath.asciidoc
docs/asciidoc/inc_filter_by_aliases.asciidoc
docs/asciidoc/inc_filter_chaining.asciidoc
docs/asciidoc/inc_kinds.asciidoc
elasticsearch_curator_internal.egg-info/PKG-INFO
elasticsearch_curator_internal.egg-info/SOURCES.txt
elasticsearch_curator_internal.egg-info/dependency_links.txt
elasticsearch_curator_internal.egg-info/entry_points.txt
elasticsearch_curator_internal.egg-info/requires.txt
elasticsearch_curator_internal.egg-info/top_level.txt
