Metadata-Version: 1.1
Name: elasticsearch-curator-internal
Version: 5.8.5
Summary: Tending your Elasticsearch indices
Home-page: http://github.com/elastic/curator
Author: Elastic
Author-email: info@elastic.co
License: Apache License, Version 2.0
Download-URL: https://github.com/elastic/curator/tarball/v5.8.5
Keywords: elasticsearch time-series indexed index-expiry
Platform: UNKNOWN
Classifier: Intended Audience :: Developers
Classifier: Intended Audience :: System Administrators
Classifier: License :: OSI Approved :: Apache Software License
Classifier: Operating System :: OS Independent
Classifier: Programming Language :: Python
Classifier: Programming Language :: Python :: 3.7
Classifier: Programming Language :: Python :: 3.8
Classifier: Programming Language :: Python :: 3.9
